pyscf/dftd3/libdftd3.so
pyscf/dftd3/itrf.py
pyscf/dftd3/__init__.py
pyscf/dftd3/test/test_dftd3.py
pyscf_dftd3-0.0.1.dist-info/LICENSE
pyscf_dftd3-0.0.1.dist-info/RECORD
pyscf_dftd3-0.0.1.dist-info/top_level.txt
pyscf_dftd3-0.0.1.dist-info/METADATA
pyscf_dftd3-0.0.1.dist-info/WHEEL
pyscf_dftd3.libs/libgfortran-ed201abd.so.3.0.0
