Metadata-Version: 2.1
Name: pyscf-dftd3
Version: 0.0.1
Summary: DFT-D3 python interface
Home-page: UNKNOWN
Author: UNKNOWN
Author-email: UNKNOWN
License: UNKNOWN
Platform: UNKNOWN
Requires-Dist: pyscf
Requires-Dist: numpy
